JavaShejimoshiZuijiaShijianChuyi/README.md
JavaShejimoshiZuijiaShijianChuyi/__init__.py
JavaShejimoshiZuijiaShijianChuyi/__main__.py
JavaShejimoshiZuijiaShijianChuyi/file.epub
JavaShejimoshiZuijiaShijianChuyi/index.html
JavaShejimoshiZuijiaShijianChuyi/css/__init__.py
JavaShejimoshiZuijiaShijianChuyi/css/annotations.css
JavaShejimoshiZuijiaShijianChuyi/css/main.css
JavaShejimoshiZuijiaShijianChuyi/css/normalize.css
JavaShejimoshiZuijiaShijianChuyi/css/popup.css
JavaShejimoshiZuijiaShijianChuyi/font/__init__.py
JavaShejimoshiZuijiaShijianChuyi/font/fontello.eot
JavaShejimoshiZuijiaShijianChuyi/font/fontello.svg
JavaShejimoshiZuijiaShijianChuyi/font/fontello.ttf
JavaShejimoshiZuijiaShijianChuyi/font/fontello.woff
JavaShejimoshiZuijiaShijianChuyi/img/__init__.py
JavaShejimoshiZuijiaShijianChuyi/img/annotator-glyph-sprite.png
JavaShejimoshiZuijiaShijianChuyi/img/annotator-icon-sprite.png
JavaShejimoshiZuijiaShijianChuyi/img/apple-touch-icon.png
JavaShejimoshiZuijiaShijianChuyi/img/cancelfullscreen.png
JavaShejimoshiZuijiaShijianChuyi/img/close.png
JavaShejimoshiZuijiaShijianChuyi/img/fullscreen.png
JavaShejimoshiZuijiaShijianChuyi/img/loader.gif
JavaShejimoshiZuijiaShijianChuyi/img/menu-icon.png
JavaShejimoshiZuijiaShijianChuyi/img/save.png
JavaShejimoshiZuijiaShijianChuyi/img/saved.png
JavaShejimoshiZuijiaShijianChuyi/img/settings-s.png
JavaShejimoshiZuijiaShijianChuyi/img/settings.png
JavaShejimoshiZuijiaShijianChuyi/img/star.png
JavaShejimoshiZuijiaShijianChuyi/js/__init__.py
JavaShejimoshiZuijiaShijianChuyi/js/epub.js
JavaShejimoshiZuijiaShijianChuyi/js/epub.min.js
JavaShejimoshiZuijiaShijianChuyi/js/epub.min.map
JavaShejimoshiZuijiaShijianChuyi/js/hooks.min.js
JavaShejimoshiZuijiaShijianChuyi/js/hooks.min.map
JavaShejimoshiZuijiaShijianChuyi/js/reader.js
JavaShejimoshiZuijiaShijianChuyi/js/reader.js.map
JavaShejimoshiZuijiaShijianChuyi/js/reader.min.js
JavaShejimoshiZuijiaShijianChuyi/js/reader.min.map
JavaShejimoshiZuijiaShijianChuyi/js/hooks/__init__.py
java_shejimoshi_zuijia_shijian_chuyi-2024.3.5.0.dist-info/METADATA
java_shejimoshi_zuijia_shijian_chuyi-2024.3.5.0.dist-info/WHEEL
java_shejimoshi_zuijia_shijian_chuyi-2024.3.5.0.dist-info/entry_points.txt
java_shejimoshi_zuijia_shijian_chuyi-2024.3.5.0.dist-info/top_level.txt
java_shejimoshi_zuijia_shijian_chuyi-2024.3.5.0.dist-info/RECORD
